phonenumberchecker/__init__.py
phonenumberchecker/phonenumberchecker.py
phonenumberchecker/data/data_acma_.csv.gz
phonenumberchecker/data/data_prefixes_.txt
phonenumberchecker-0.0.5.dist-info/METADATA
phonenumberchecker-0.0.5.dist-info/RECORD
phonenumberchecker-0.0.5.dist-info/WHEEL
phonenumberchecker-0.0.5.dist-info/top_level.txt
