Metadata-Version: 2.1
Name: phonenumberchecker
Version: 0.0.5
Summary: Check any Australian numbers
Home-page: https://github.com/i9k/phonenumberchecker
Author: Igor Korostil
Author-email: eeghor@gmail.com
License: MIT
Keywords: phone number
Platform: UNKNOWN
Classifier: Development Status :: 3 - Alpha
Classifier: Programming Language :: Python :: 3.6
Classifier: Topic :: Text Processing
Classifier: Topic :: Text Processing :: Filters
Requires-Python: >=3.6
Requires-Dist: pandas
